dff/dff.v
`timescale 1ns/1ns

module dff (
  input logic clk, d,
  output logic q
);

always @(posedge clk) begin
  q <= d;
end

  // Dump VCD
  initial begin
    $dumpfile("VCD_File.vcd");
    $dumpvars;
  end

endmodule

dff/VCD_File.vcd
$date
	Sat Dec 23 11:26:22 2023
$end
$version
	Icarus Verilog
$end
$timescale
	1ps
$end
$scope module dff $end
$var wire 1 ! clk $end
$var wire 1 " d $end
$var reg 1 # q $end
$upscope $end
$enddefinitions $end
#0
$dumpvars
x#
0"
0!
$end
#5000
0#
1!
#10000
0!
#15000
1"
1!
#20000
0!
#25000
0"
1#
1!
#30000
0!
#35000
1"
0#
1!
#40000
0!
#45000
0"
1#
1!
#50000
0!
#55000
1"
0#
1!
#60000
0!
#65000
0"
1#
1!
#70000
0!
#75000
1"
0#
1!
#80000
0!
#85000
0"
1#
1!
#90000
0!
#95000
1"
0#
1!
#100000
0!
#105000
0"
1#
1!
#110000
0!
#115000
1"
0#
1!
#120000
0!
#125000
0"
1#
1!
#130000
0!
#135000
1"
0#
1!
#140000
0!
#145000
0"
1#
1!
#150000
0!
#155000
1"
0#
1!
#160000
0!
#165000
0"
1#
1!
#170000
0!
#175000
1"
0#
1!
#180000
0!
#185000
0"
1#
1!
#190000
0!
#195000
1"
0#
1!
#200000
0!
#205000
1#
1!
